easytorch/__init__.py
easytorch/config.py
easytorch/train.py
easytorch/version.py
easytorch/core/__init__.py
easytorch/core/checkpoint.py
easytorch/core/data_loader.py
easytorch/core/launcher.py
easytorch/core/meter_pool.py
easytorch/core/optimizer_builder.py
easytorch/core/runner.py
easytorch/easyoptim/__init__.py
easytorch/easyoptim/easy_lr_scheduler.py
easytorch/easyoptim/lamb.py
easytorch/utils/__init__.py
easytorch/utils/data_prefetcher.py
easytorch/utils/dist.py
easytorch/utils/env.py
easytorch/utils/logging.py
easytorch/utils/timer.py
xtorch-1.0.0.dist-info/LICENSE
xtorch-1.0.0.dist-info/METADATA
xtorch-1.0.0.dist-info/WHEEL
xtorch-1.0.0.dist-info/entry_points.txt
xtorch-1.0.0.dist-info/top_level.txt
xtorch-1.0.0.dist-info/RECORD
