Metadata-Version: 2.1
Name: xtorch
Version: 1.0.0
Summary: Simple and powerful pytorch framework.
Home-page: https://github.com/cnstark/easytorch
Author: Yuhao Wang
Author-email: yuhaow97@gmail.com
License: Apache License 2.0
Keywords: pytorch,deep learning
Platform: UNKNOWN
Classifier: Development Status :: 4 - Beta
Classifier: License :: OSI Approved :: Apache Software License
Classifier: Operating System :: OS Independent
Classifier: Programming Language :: Python :: 3
Classifier: Programming Language :: Python :: 3.7
Classifier: Programming Language :: Python :: 3.8
Classifier: Programming Language :: Python :: 3.9
Classifier: Topic :: Utilities
Requires-Dist: torch (>=1.7)
Requires-Dist: easydict
Requires-Dist: tensorboard
Requires-Dist: tqdm
